MANIFEST.in
setup.py
cli/__init__.py
cli/config.py
cli/driver.py
cli/utils.py
cli/action/Action.py
cli/action/__init__.py
homework_cli.egg-info/PKG-INFO
homework_cli.egg-info/SOURCES.txt
homework_cli.egg-info/dependency_links.txt
homework_cli.egg-info/entry_points.txt
homework_cli.egg-info/requires.txt
homework_cli.egg-info/top_level.txt