Metadata-Version: 1.0
Name: homework-cli
Version: 0.1
Summary: homework-cli
Home-page: http://fullstack.love
Author: phantooom
Author-email: zouruixp@sina.com
License: MIT
Keywords: homework
Platform: UNKNOWN
